skipi/__init__.py
skipi/collection.py
skipi/convolution.py
skipi/domain.py
skipi/error.py
skipi/fourier.py
skipi/function.py
skipi/norm.py
skipi/parameter.py
skipi/plot.py
skipi/statistics.py
skipi/util.py
skipi/plotter/__init__.py
skipi/plotter/reflectometry.py
tests/__init__.py
tests/helper.py
tests/fourier/__init__.py
tests/fourier/test_compare_fourier_matrix.py
tests/fourier/test_fourier_identity.py
tests/fourier/test_fourier_with_analytical_functions.py
tests/fourier/test_linearity.py
tests/fourier/test_splitting.py
tests/function/__init__.py
tests/function/test_domain.py
tests/function/test_gradient.py
tests/function/test_integration.py
tests/function/test_math_operations.py
tests/function/test_operations.py
tests/function/test_oversample.py
tests/function/test_piecewise.py
tests/function/test_shift.py
skipi-0.1.7.dist-info/LICENSE
skipi-0.1.7.dist-info/METADATA
skipi-0.1.7.dist-info/WHEEL
skipi-0.1.7.dist-info/top_level.txt
skipi-0.1.7.dist-info/RECORD
