Metadata-Version: 2.1
Name: skipi
Version: 0.1.7
Summary: Intuitive package to easily work with mathematical functions
Home-page: https://github.com/TUM-E21-ThinFilms/skipi
Author: Alexander Book
Author-email: alexander.book@frm2.tum.de
License: MIT
Keywords: scientific,mathematical transforms
Classifier: Development Status :: 3 - Alpha
Classifier: Intended Audience :: Developers
Classifier: Intended Audience :: Education
Classifier: Intended Audience :: Science/Research
Classifier: License :: OSI Approved :: MIT License
Classifier: Topic :: Scientific/Engineering :: Mathematics
Classifier: Programming Language :: Python :: 3
Classifier: Programming Language :: Python :: 3.4
Classifier: Programming Language :: Python :: 3.5
Classifier: Programming Language :: Python :: 3.6
Classifier: Programming Language :: Python :: 3.7
Classifier: Programming Language :: Python :: 3.8
License-File: LICENSE
Requires-Dist: numpy
Requires-Dist: scipy
Requires-Dist: matplotlib
